persai/__init__.py
persai/big_five.py
persai/open_ai.py
persai/x_data_cleaner.py
persai-0.0.5.dist-info/LICENSE
persai-0.0.5.dist-info/METADATA
persai-0.0.5.dist-info/WHEEL
persai-0.0.5.dist-info/top_level.txt
persai-0.0.5.dist-info/RECORD
