Metadata-Version: 2.1
Name: persai
Version: 0.0.5
Summary: Big Five Personality Analysis based on Twitter (X) posts.
Home-page: https://github.com/yachty66/persai
Author: Max Hager
Author-email: maxhager28@gmail.com
License-File: LICENSE
Requires-Dist: openai
